Workbook

Sheet Master Dashboard
A1: TRU CONNECT: ENGINEERING ROADMAP
A2: Source of truth: Documents 00–09. See 'Notes & Assumptions' sheet for scope decisions.
A4: Sheet | B4: Total Tasks | C4: ⬜ Not Started | D4: 🟦 In Progress | E4: 🟨 Testing | F4: 🟪 Review | G4: 🟩 Complete | H4: 🔴 Blocked | I4: % Complete
A5: Backend | B5: =COUNTA(Backend!$A$2:$A$156) -> 155 | C5: =COUNTIF(Backend!$H$2:$H$156,"⬜ Not Started") -> 129 | D5: =COUNTIF(Backend!$H$2:$H$156,"🟦 In Progress") -> 26 | E5: =COUNTIF(Backend!$H$2:$H$156,"🟨 Testing") -> 0 | F5: =COUNTIF(Backend!$H$2:$H$156,"🟪 Review") -> 0 | G5: =COUNTIF(Backend!$H$2:$H$156,"🟩 Complete") -> 0 | H5: =COUNTIF(Backend!$H$2:$H$156,"🔴 Blocked") -> 0 | I5: =IFERROR(G5/B5,0) -> 0
A6: Frontend | B6: =COUNTA(Frontend!$A$2:$A$88) -> 87 | C6: =COUNTIF(Frontend!$H$2:$H$88,"⬜ Not Started") -> 72 | D6: =COUNTIF(Frontend!$H$2:$H$88,"🟦 In Progress") -> 8 | E6: =COUNTIF(Frontend!$H$2:$H$88,"🟨 Testing") -> 0 | F6: =COUNTIF(Frontend!$H$2:$H$88,"🟪 Review") -> 0 | G6: =COUNTIF(Frontend!$H$2:$H$88,"🟩 Complete") -> 7 | H6: =COUNTIF(Frontend!$H$2:$H$88,"🔴 Blocked") -> 0 | I6: =IFERROR(G6/B6,0) -> 0.08045977
A7: Database | B7: =COUNTA(Database!$A$2:$A$59) -> 58 | C7: =COUNTIF(Database!$H$2:$H$59,"⬜ Not Started") -> 50 | D7: =COUNTIF(Database!$H$2:$H$59,"🟦 In Progress") -> 8 | E7: =COUNTIF(Database!$H$2:$H$59,"🟨 Testing") -> 0 | F7: =COUNTIF(Database!$H$2:$H$59,"🟪 Review") -> 0 | G7: =COUNTIF(Database!$H$2:$H$59,"🟩 Complete") -> 0 | H7: =COUNTIF(Database!$H$2:$H$59,"🔴 Blocked") -> 0 | I7: =IFERROR(G7/B7,0) -> 0
A8: API | B8: =COUNTA(API!$A$2:$A$100) -> 99 | C8: =COUNTIF(API!$H$2:$H$100,"⬜ Not Started") -> 90 | D8: =COUNTIF(API!$H$2:$H$100,"🟦 In Progress") -> 9 | E8: =COUNTIF(API!$H$2:$H$100,"🟨 Testing") -> 0 | F8: =COUNTIF(API!$H$2:$H$100,"🟪 Review") -> 0 | G8: =COUNTIF(API!$H$2:$H$100,"🟩 Complete") -> 0 | H8: =COUNTIF(API!$H$2:$H$100,"🔴 Blocked") -> 0 | I8: =IFERROR(G8/B8,0) -> 0
A9: Trust Engine | B9: =COUNTA('Trust Engine'!$A$2:$A$35) -> 34 | C9: =COUNTIF('Trust Engine'!$H$2:$H$35,"⬜ Not Started") -> 34 | D9: =COUNTIF('Trust Engine'!$H$2:$H$35,"🟦 In Progress") -> 0 | E9: =COUNTIF('Trust Engine'!$H$2:$H$35,"🟨 Testing") -> 0 | F9: =COUNTIF('Trust Engine'!$H$2:$H$35,"🟪 Review") -> 0 | G9: =COUNTIF('Trust Engine'!$H$2:$H$35,"🟩 Complete") -> 0 | H9: =COUNTIF('Trust Engine'!$H$2:$H$35,"🔴 Blocked") -> 0 | I9: =IFERROR(G9/B9,0) -> 0
A10: Testing | B10: =COUNTA(Testing!$A$2:$A$36) -> 35 | C10: =COUNTIF(Testing!$H$2:$H$36,"⬜ Not Started") -> 33 | D10: =COUNTIF(Testing!$H$2:$H$36,"🟦 In Progress") -> 0 | E10: =COUNTIF(Testing!$H$2:$H$36,"🟨 Testing") -> 2 | F10: =COUNTIF(Testing!$H$2:$H$36,"🟪 Review") -> 0 | G10: =COUNTIF(Testing!$H$2:$H$36,"🟩 Complete") -> 0 | H10: =COUNTIF(Testing!$H$2:$H$36,"🔴 Blocked") -> 0 | I10: =IFERROR(G10/B10,0) -> 0
A11: DevOps | B11: =COUNTA(DevOps!$A$2:$A$16) -> 15 | C11: =COUNTIF(DevOps!$H$2:$H$16,"⬜ Not Started") -> 15 | D11: =COUNTIF(DevOps!$H$2:$H$16,"🟦 In Progress") -> 0 | E11: =COUNTIF(DevOps!$H$2:$H$16,"🟨 Testing") -> 0 | F11: =COUNTIF(DevOps!$H$2:$H$16,"🟪 Review") -> 0 | G11: =COUNTIF(DevOps!$H$2:$H$16,"🟩 Complete") -> 0 | H11: =COUNTIF(DevOps!$H$2:$H$16,"🔴 Blocked") -> 0 | I11: =IFERROR(G11/B11,0) -> 0
A12: Future Phases | B12: =COUNTA('Future Phases'!$A$2:$A$25) -> 24 | C12: =COUNTIF('Future Phases'!$H$2:$H$25,"⬜ Not Started") -> 24 | D12: =COUNTIF('Future Phases'!$H$2:$H$25,"🟦 In Progress") -> 0 | E12: =COUNTIF('Future Phases'!$H$2:$H$25,"🟨 Testing") -> 0 | F12: =COUNTIF('Future Phases'!$H$2:$H$25,"🟪 Review") -> 0 | G12: =COUNTIF('Future Phases'!$H$2:$H$25,"🟩 Complete") -> 0 | H12: =COUNTIF('Future Phases'!$H$2:$H$25,"🔴 Blocked") -> 0 | I12: =IFERROR(G12/B12,0) -> 0
A13: GRAND TOTAL | B13: =SUM(B5:B12) -> 507 | C13: =SUM(C5:C12) -> 447 | D13: =SUM(D5:D12) -> 51 | E13: =SUM(E5:E12) -> 2 | F13: =SUM(F5:F12) -> 0 | G13: =SUM(G5:G12) -> 7 | H13: =SUM(H5:H12) -> 0 | I13: =IFERROR(G13/B13,0) -> 0.013806706
A16: Priority Legend | C16: Status Legend
A17: 🟥 Critical | C17: ⬜ Not Started
A18: 🟧 High | C18: 🟦 In Progress
A19: 🟨 Medium | C19: 🟨 Testing
A20: 🟩 Low | C20: 🟪 Review
C21: 🟩 Complete
C22: 🔴 Blocked

Sheet Backend
A1: ID | B1: Module | C1: Feature | D1: Task | E1: Priority | F1: Dependencies | G1: Assigned To | H1: Status
A2: BE-001 | B2: Authentication Domain | C2: users | D2: Create `users` Model (SQLAlchemy ORM) | E2: 🟥 Critical | F2: DB-001 | H2: 🟦 In Progress
A3: BE-002 | B3: Authentication Domain | C3: users | D3: Create `users` Repository (data access layer) | E3: 🟥 Critical | F3: BE-001 | H3: 🟦 In Progress
A4: BE-003 | B4: Authentication Domain | C4: roles | D4: Create `roles` Model (SQLAlchemy ORM) | E4: 🟧 High | F4: DB-002 | H4: 🟦 In Progress
A5: BE-004 | B5: Authentication Domain | C5: roles | D5: Create `roles` Repository (data access layer) | E5: 🟧 High | F5: BE-003 | H5: 🟦 In Progress
A6: BE-005 | B6: Authentication Domain | C6: permissions | D6: Create `permissions` Model (SQLAlchemy ORM) | E6: 🟧 High | F6: DB-003 | H6: 🟦 In Progress
A7: BE-006 | B7: Authentication Domain | C7: permissions | D7: Create `permissions` Repository (data access layer) | E7: 🟧 High | F7: BE-005 | H7: 🟦 In Progress
A8: BE-007 | B8: Authentication Domain | C8: role_permissions | D8: Create `role_permissions` Model (SQLAlchemy ORM) | E8: 🟧 High | F8: DB-004 | H8: 🟦 In Progress
A9: BE-008 | B9: Authentication Domain | C9: role_permissions | D9: Create `role_permissions` Repository (data access layer) | E9: 🟧 High | F9: BE-007 | H9: 🟦 In Progress
A10: BE-009 | B10: Authentication Domain | C10: user_roles | D10: Create `user_roles` Model (SQLAlchemy ORM) | E10: 🟧 High | F10: DB-005 | H10: 🟦 In Progress
A11: BE-010 | B11: Authentication Domain | C11: user_roles | D11: Create `user_roles` Repository (data access layer) | E11: 🟧 High | F11: BE-009 | H11: 🟦 In Progress
A12: BE-011 | B12: Authentication Domain | C12: refresh_tokens | D12: Create `refresh_tokens` Model (SQLAlchemy ORM) | E12: 🟧 High | F12: DB-006 | H12: 🟦 In Progress
A13: BE-012 | B13: Authentication Domain | C13: refresh_tokens | D13: Create `refresh_tokens` Repository (data access layer) | E13: 🟧 High | F13: BE-011 | H13: 🟦 In Progress
... A156: BE-155 | B156: Cross-Domain | C156: Core Infrastructure | D156: JWT Service — issue, verify, refresh tokens (Document 05 §5.1) | E156: 🟥 Critical | F156: None | H156: ⬜ Not Started

Sheet Frontend
A1: ID | B1: Module | C1: Feature | D1: Task | E1: Priority | F1: Dependencies | G1: Assigned To | H1: Status
A2: FE-001 | B2: Shared / Pre-Auth | C2: Screens | D2: Build Landing Screen (two-slide role introduction) Screen | E2: 🟧 High | F2: Corresponding API endpoint(s) | H2: 🟩 Complete
A3: FE-002 | B3: Shared / Pre-Auth | C3: Screens | D3: Build Login Screen Screen | E3: 🟧 High | F3: Corresponding API endpoint(s) | H3: 🟩 Complete
A4: FE-003 | B4: Shared / Pre-Auth | C4: Screens | D4: Build Register Screen Screen | E4: 🟧 High | F4: Corresponding API endpoint(s) | H4: 🟩 Complete
A5: FE-004 | B5: Shared / Pre-Auth | C5: Screens | D5: Build Google Authentication flow screen Screen | E5: 🟧 High | F5: Corresponding API endpoint(s) | H5: ⬜ Not Started
A6: FE-005 | B6: Business (Doc01 §8.2) | C6: Screens | D6: Build Business Home Dashboard Screen | E6: 🟧 High | F6: Corresponding API endpoint(s) | H6: 🟦 In Progress
A7: FE-006 | B7: Business (Doc01 §8.2) | C7: Screens | D7: Build Business Profile Screen | E7: 🟧 High | F7: Corresponding API endpoint(s) | H7: ⬜ Not Started
A8: FE-007 | B8: Business (Doc01 §8.2) | C8: Screens | D8: Build Verification Screen | E8: 🟧 High | F8: Corresponding API endpoint(s) | H8: ⬜ Not Started
A9: FE-008 | B9: Business (Doc01 §8.2) | C9: Screens | D9: Build Wallet (Phase 1 placeholder — Document 01 §8.2) Screen | E9: 🟩 Low | F9: Corresponding API endpoint(s) | H9: ⬜ Not Started
A10: FE-009 | B10: Business (Doc01 §8.2) | C10: Screens | D10: Build Saved Suppliers Screen | E10: 🟧 High | F10: Corresponding API endpoint(s) | H10: ⬜ Not Started
A11: FE-010 | B11: Business (Doc01 §8.2) | C11: Screens | D11: Add Loading State (skeleton) to Saved Suppliers — Document 02 §2.3 | E11: 🟨 Medium | F11: FE-009 | H11: ⬜ Not Started
A12: FE-011 | B12: Business (Doc01 §8.2) | C12: Screens | D12: Add Empty State to Saved Suppliers — Document 02 §2.3 / Document 03 §5.9 | E12: 🟨 Medium | F12: FE-009 | H12: ⬜ Not Started
A13: FE-012 | B13: Business (Doc01 §8.2) | C13: Screens | D13: Build Business Documents Screen | E13: 🟧 High | F13: Corresponding API endpoint(s) | H13: ⬜ Not Started
... A88: FE-087 | B88: Cross-Cutting | C88: Animations | D88: Implement brief status-change confirmation animation (e.g. order accepted — Document 02 §12) | E88: 🟩 Low | F88: None | H88: ⬜ Not Started

Sheet Database
A1: ID | B1: Module | C1: Feature | D1: Task | E1: Priority | F1: Dependencies | G1: Assigned To | H1: Status
A2: DB-001 | B2: Authentication Domain | C2: users | D2: Create `users` table migration (columns, PK, FK, timestamps — Document 04) | E2: 🟥 Critical | F2: None | H2: 🟦 In Progress
A3: DB-002 | B3: Authentication Domain | C3: roles | D3: Create `roles` table migration (columns, PK, FK, timestamps — Document 04) | E3: 🟧 High | F3: None | H3: 🟦 In Progress
A4: DB-003 | B4: Authentication Domain | C4: permissions | D4: Create `permissions` table migration (columns, PK, FK, timestamps — Document 04) | E4: 🟧 High | F4: None | H4: 🟦 In Progress
A5: DB-004 | B5: Authentication Domain | C5: role_permissions | D5: Create `role_permissions` table migration (columns, PK, FK, timestamps — Document 04) | E5: 🟧 High | F5: None | H5: 🟦 In Progress
A6: DB-005 | B6: Authentication Domain | C6: user_roles | D6: Create `user_roles` table migration (columns, PK, FK, timestamps — Document 04) | E6: 🟧 High | F6: None | H6: 🟦 In Progress
A7: DB-006 | B7: Authentication Domain | C7: refresh_tokens | D7: Create `refresh_tokens` table migration (columns, PK, FK, timestamps — Document 04) | E7: 🟧 High | F7: None | H7: 🟦 In Progress
A8: DB-007 | B8: Authentication Domain | C8: login_history | D8: Create `login_history` table migration (columns, PK, FK, timestamps — Document 04) | E8: 🟧 High | F8: None | H8: 🟦 In Progress
A9: DB-008 | B9: Authentication Domain | C9: password_reset_tokens | D9: Create `password_reset_tokens` table migration (columns, PK, FK, timestamps — Document 04) | E9: 🟧 High | F9: None | H9: 🟦 In Progress
A10: DB-009 | B10: Business Domain | C10: businesses | D10: Create `businesses` table migration (columns, PK, FK, timestamps — Document 04) | E10: 🟥 Critical | F10: None | H10: ⬜ Not Started
A11: DB-010 | B11: Business Domain | C11: business_profiles | D11: Create `business_profiles` table migration (columns, PK, FK, timestamps — Document 04) | E11: 🟧 High | F11: None | H11: ⬜ Not Started
A12: DB-011 | B12: Business Domain | C12: business_addresses | D12: Create `business_addresses` table migration (columns, PK, FK, timestamps — Document 04) | E12: 🟧 High | F12: None | H12: ⬜ Not Started
A13: DB-012 | B13: Business Domain | C13: business_categories | D13: Create `business_categories` table migration (columns, PK, FK, timestamps — Document 04) | E13: 🟧 High | F13: None | H13: ⬜ Not Started
... A59: DB-058 | B59: Cross-Domain | C59: Future-Scoped Schema | D59: Reserve Financial Domain placeholder tables (wallets, wallet_transactions, credit_applications) per Document 04 §6 — no implementation in Phase 1 | E59: 🟩 Low | F59: None | H59: ⬜ Not Started

Sheet API
A1: ID | B1: Module | C1: Feature | D1: Task | E1: Priority | F1: Dependencies | G1: Assigned To | H1: Status
A2: API-001 | B2: Authentication Domain | C2: auth | D2: POST /auth/register — Create account; role assigned via user_roles at registration | E2: 🟥 Critical | F2: DB-001 | H2: 🟦 In Progress
A3: API-002 | B3: Authentication Domain | C3: auth | D3: POST /auth/login — Authenticate with email/password; record login_history; return JWT + refresh token | E3: 🟥 Critical | F3: DB-001 | H3: 🟦 In Progress
A4: API-003 | B4: Authentication Domain | C4: auth | D4: POST /auth/google — Authenticate/register via Google OAuth token; return JWT + refresh token | E4: 🟥 Critical | F4: DB-001 | H4: 🟦 In Progress
A5: API-004 | B5: Authentication Domain | C5: auth | D5: POST /auth/refresh — Exchange a valid refresh_token for a new JWT | E5: 🟥 Critical | F5: DB-001 | H5: 🟦 In Progress
A6: API-005 | B6: Authentication Domain | C6: auth | D6: POST /auth/logout — Revoke the current refresh_token | E6: 🟥 Critical | F6: DB-001 | H6: 🟦 In Progress
A7: API-006 | B7: Authentication Domain | C7: auth | D7: POST /auth/forgot-password — Initiate password reset flow; create password_reset_tokens entry | E7: 🟥 Critical | F7: DB-001 | H7: 🟦 In Progress
A8: API-007 | B8: Authentication Domain | C8: auth | D8: POST /auth/reset-password — Complete password reset flow using a valid reset token | E8: 🟥 Critical | F8: DB-001 | H8: 🟦 In Progress
A9: API-008 | B9: Authentication Domain | C9: auth | D9: GET /auth/me/roles — List roles assigned to the authenticated user | E9: 🟥 Critical | F9: DB-001 | H9: 🟦 In Progress
A10: API-009 | B10: Authentication Domain | C10: auth | D10: GET /auth/me/login-history — List recent login_history entries for the authenticated user | E10: 🟥 Critical | F10: DB-001 | H10: 🟦 In Progress
A11: API-010 | B11: Business Domain | C11: businesses | D11: GET /businesses/me — Get authenticated business's own profile | E11: 🟧 High | F11: DB-009 | H11: ⬜ Not Started
A12: API-011 | B12: Business Domain | C12: businesses | D12: PUT /businesses/me — Update own business profile | E12: 🟧 High | F12: DB-009 | H12: ⬜ Not Started
A13: API-012 | B13: Business Domain | C13: businesses | D13: GET /businesses/me/dashboard — Aggregated dashboard payload (today's orders, pending orders, nearby suppliers, recommended products, recent activity) | E13: 🟧 High | F13: DB-009 | H13: ⬜ Not Started
... A100: API-099 | B100: Platform Domain | C100: provinces | D100: GET /provinces/{id}/cities — List cities within a province | E100: 🟨 Medium | F100: DB-040 | H100: ⬜ Not Started

Sheet Trust Engine
A1: ID | B1: Module | C1: Feature | D1: Task | E1: Priority | F1: Dependencies | G1: Assigned To | H1: Status
A2: TE-001 | B2: Trust Domain | C2: Digital Business Profile | D2: Calculate orders_count (completed orders only) — Document 07 §2 | E2: 🟧 High | F2: Order/Question/Verification event pipeline | H2: ⬜ Not Started
A3: TE-002 | B3: Trust Domain | C3: Digital Business Profile | D3: Calculate suppliers_count (distinct suppliers with ≥1 completed order) — Document 07 §2 | E3: 🟧 High | F3: Order/Question/Verification event pipeline | H3: ⬜ Not Started
A4: TE-003 | B4: Trust Domain | C4: Digital Business Profile | D4: Calculate average_order_value — Document 07 §2 | E4: 🟧 High | F4: Order/Question/Verification event pipeline | H4: ⬜ Not Started
A5: TE-004 | B5: Trust Domain | C5: Digital Business Profile | D5: Calculate largest_order_value — Document 07 §2 | E5: 🟨 Medium | F5: Order/Question/Verification event pipeline | H5: ⬜ Not Started
A6: TE-005 | B6: Trust Domain | C6: Digital Business Profile | D6: Calculate repeat_supplier_rate — Document 07 §2 | E6: 🟧 High | F6: Order/Question/Verification event pipeline | H6: ⬜ Not Started
A7: TE-006 | B7: Trust Domain | C7: Digital Business Profile | D7: Calculate average_payment_time_days (Phase 1 proxy: order completion time) — Document 07 §2 | E7: 🟨 Medium | F7: Order/Question/Verification event pipeline | H7: ⬜ Not Started
A8: TE-007 | B8: Trust Domain | C8: Digital Business Profile | D8: Calculate business_growth_percentage (rolling period volume/value change) — Document 07 §2 | E8: 🟧 High | F8: Order/Question/Verification event pipeline | H8: ⬜ Not Started
A9: TE-008 | B9: Trust Domain | C9: Digital Business Profile | D9: Derive Risk Level (low/medium/high) from Trust + Risk Signals — Document 07 §2, §6 | E9: 🟧 High | F9: Order/Question/Verification event pipeline | H9: ⬜ Not Started
A10: TE-009 | B10: Trust Domain | C10: Relationship Health | D10: Signal: order frequency between business-supplier pair — Document 07 §3 | E10: 🟧 High | F10: Order/Question/Verification event pipeline | H10: ⬜ Not Started
A11: TE-010 | B11: Trust Domain | C11: Relationship Health | D11: Signal: recency of last interaction — Document 07 §3 | E11: 🟧 High | F11: Order/Question/Verification event pipeline | H11: ⬜ Not Started
A12: TE-011 | B12: Trust Domain | C12: Relationship Health | D12: Signal: order completion rate within the pair — Document 07 §3 | E12: 🟧 High | F12: Order/Question/Verification event pipeline | H12: ⬜ Not Started
A13: TE-012 | B13: Trust Domain | C13: Relationship Health | D13: Signal: Business Question responsiveness between the pair — Document 07 §3 | E13: 🟨 Medium | F13: Order/Question/Verification event pipeline | H13: ⬜ Not Started
... A35: TE-034 | B35: Trust Domain | C35: Credit Readiness | D35: Define configurable Credit Readiness threshold parameters (Phase 3 prep, no UI in Phase 1) — Document 07 §13 | E35: 🟩 Low | F35: Order/Question/Verification event pipeline | H35: ⬜ Not Started

Sheet Testing
A1: ID | B1: Module | C1: Feature | D1: Task | E1: Priority | F1: Dependencies | G1: Assigned To | H1: Status
A2: QA-001 | B2: Authentication Domain | C2: Unit Tests | D2: Auth unit & integration tests — register, login, refresh, logout | E2: 🟥 Critical | F2: Corresponding implementation task complete | H2: 🟨 Testing
A3: QA-002 | B3: Authentication Domain | C3: Security Tests | D3: JWT validation & role-based access control tests | E3: 🟥 Critical | F3: Corresponding implementation task complete | H3: 🟨 Testing
A4: QA-003 | B4: Business Domain | C4: Unit Tests | D4: Business Service unit tests (profile CRUD, addresses, documents) | E4: 🟧 High | F4: Corresponding implementation task complete | H4: ⬜ Not Started
A5: QA-004 | B5: Business Domain | C5: Repository Tests | D5: Business Repository tests against seeded database | E5: 🟨 Medium | F5: Corresponding implementation task complete | H5: ⬜ Not Started
A6: QA-005 | B6: Supplier Domain | C6: Unit Tests | D6: Product Service unit tests (create/update/publish/soft-delete) | E6: 🟧 High | F6: Corresponding implementation task complete | H6: ⬜ Not Started
A7: QA-006 | B7: Supplier Domain | C7: Repository Tests | D7: Supplier Repository tests against seeded database | E7: 🟨 Medium | F7: Corresponding implementation task complete | H7: ⬜ Not Started
A8: QA-007 | B8: Marketplace Domain | C8: Integration Tests | D8: Order lifecycle integration test (place → accept → complete) | E8: 🟥 Critical | F8: Corresponding implementation task complete | H8: ⬜ Not Started
A9: QA-008 | B9: Marketplace Domain | C9: Integration Tests | D9: Order rejection workflow integration test | E9: 🟧 High | F9: Corresponding implementation task complete | H9: ⬜ Not Started
A10: QA-009 | B10: Marketplace Domain | C10: Integration Tests | D10: Business Question + Supplier Response workflow test | E10: 🟧 High | F10: Corresponding implementation task complete | H10: ⬜ Not Started
A11: QA-010 | B11: Marketplace Domain | C11: Business Rule Tests | D11: Enforce single-supplier-cart rule test (Document 06 §10) | E11: 🟧 High | F11: Corresponding implementation task complete | H11: ⬜ Not Started
A12: QA-011 | B12: Marketplace Domain | C12: Business Rule Tests | D12: Enforce minimum order quantity validation test (Document 06 §10) | E12: 🟧 High | F12: Corresponding implementation task complete | H12: ⬜ Not Started
A13: QA-012 | B13: Trust Domain | C13: Unit Tests | D13: Business Health Score calculation unit tests | E13: 🟧 High | F13: Corresponding implementation task complete | H13: ⬜ Not Started
... A36: QA-035 | B36: Security | C36: Security Tests | D36: Resource-ownership authorization test (supplier cannot edit another supplier's product) | E36: 🟥 Critical | F36: Corresponding implementation task complete | H36: ⬜ Not Started

Sheet DevOps
A1: ID | B1: Module | C1: Feature | D1: Task | E1: Priority | F1: Dependencies | G1: Assigned To | H1: Status
A2: OPS-001 | B2: Platform Infrastructure | C2: Environment | D2: Define environment variable schema (.env.example) for backend and mobile | E2: 🟥 Critical | F2: None | H2: ⬜ Not Started
A3: OPS-002 | B3: Platform Infrastructure | C3: Environment | D3: Separate development / staging / production configuration profiles | E3: 🟧 High | F3: None | H3: ⬜ Not Started
A4: OPS-003 | B4: Platform Infrastructure | C4: Containerization | D4: Dockerize Flask backend service | E4: 🟧 High | F4: None | H4: ⬜ Not Started
A5: OPS-004 | B5: Platform Infrastructure | C5: Containerization | D5: Dockerize PostgreSQL with persistent volume | E5: 🟧 High | F5: None | H5: ⬜ Not Started
A6: OPS-005 | B6: Platform Infrastructure | C6: CI/CD | D6: CI pipeline — lint + unit test on every pull request | E6: 🟥 Critical | F6: None | H6: ⬜ Not Started
A7: OPS-006 | B7: Platform Infrastructure | C7: CI/CD | D7: CI pipeline — build backend Docker image on merge to main | E7: 🟧 High | F7: None | H7: ⬜ Not Started
A8: OPS-007 | B8: Platform Infrastructure | C8: CI/CD | D8: CD pipeline — deploy backend to staging environment | E8: 🟧 High | F8: None | H8: ⬜ Not Started
A9: OPS-008 | B9: Platform Infrastructure | C9: CI/CD | D9: CD pipeline — deploy backend to production with manual approval gate | E9: 🟧 High | F9: None | H9: ⬜ Not Started
A10: OPS-009 | B10: Platform Infrastructure | C10: Database Ops | D10: Automated database migration pipeline (apply on deploy) | E10: 🟥 Critical | F10: None | H10: ⬜ Not Started
A11: OPS-010 | B11: Platform Infrastructure | C11: Database Ops | D11: Automated nightly database backups with retention policy | E11: 🟧 High | F11: None | H11: ⬜ Not Started
A12: OPS-011 | B12: Platform Infrastructure | C12: Observability | D12: Structured logging pipeline (aggregation + retention) | E12: 🟨 Medium | F12: None | H12: ⬜ Not Started
A13: OPS-012 | B13: Platform Infrastructure | C13: Observability | D13: Application monitoring & alerting (error rate, latency) | E13: 🟨 Medium | F13: None | H13: ⬜ Not Started
... A16: OPS-015 | B16: Platform Infrastructure | C16: API Governance | D16: Document /api/v1 versioning strategy for additive, non-breaking expansion (Document 05 §1) | E16: 🟨 Medium | F16: None | H16: ⬜ Not Started

Sheet Future Phases
A1: ID | B1: Module | C1: Feature | D1: Task | E1: Priority | F1: Dependencies | G1: Assigned To | H1: Status
A2: FUT-001 | B2: Deferred Phase 1 Endpoints | C2: Authentication | D2: Implement POST /auth/phone/request-otp (Document 05 §5.1, future) | E2: 🟩 Low | F2: Phase 1 completion | H2: ⬜ Not Started
A3: FUT-002 | B3: Deferred Phase 1 Endpoints | C3: Authentication | D3: Implement POST /auth/phone/verify-otp (Document 05 §5.1, future) | E3: 🟩 Low | F3: Phase 1 completion | H3: ⬜ Not Started
A4: FUT-003 | B4: Deferred Phase 1 Endpoints | C4: Authentication | D4: Implement biometric registration/verification endpoints (Document 05 §5.1, future) | E4: 🟩 Low | F4: Phase 1 completion | H4: ⬜ Not Started
A5: FUT-004 | B5: Deferred Phase 1 Endpoints | C5: Authentication | D5: Implement passkey registration endpoints (Document 05 §5.1, future) | E5: 🟩 Low | F5: Phase 1 completion | H5: ⬜ Not Started
A6: FUT-005 | B6: Deferred Phase 1 Endpoints | C6: Admin (Platform Administrator role) | D6: Implement GET/PUT /admin/roles, /admin/users/{id}/roles (Document 05 §5.1, Document 01 §9.3) | E6: 🟩 Low | F6: Phase 1 completion | H6: ⬜ Not Started
A7: FUT-006 | B7: Deferred Phase 1 Endpoints | C7: Admin (Platform Administrator role) | D7: Implement PUT/GET /admin/verification/requests (Document 05 §5.6, Document 01 §9.3) | E7: 🟩 Low | F7: Phase 1 completion | H7: ⬜ Not Started
A8: FUT-007 | B8: Deferred Phase 1 Endpoints | C8: Admin (Platform Administrator role) | D8: Implement GET /admin/audit-logs, /admin/system-settings (Document 05 §5.7, Document 01 §9.3) | E8: 🟩 Low | F8: Phase 1 completion | H8: ⬜ Not Started
A9: FUT-008 | B9: Deferred Phase 1 Endpoints | C9: Financial Partner role | D9: Design read-only Financial Partner access model (Document 01 §9.3, Phase 4) | E9: 🟩 Low | F9: Phase 1 completion | H9: ⬜ Not Started
A10: FUT-009 | B10: Phase 2 — Payments, Wallet, Insights | C10: Payments | D10: Design and implement in-app payment processing for orders (Document 08) | E10: 🟨 Medium | F10: Phase 1 completion | H10: ⬜ Not Started
A11: FUT-010 | B11: Phase 2 — Payments, Wallet, Insights | C11: Wallet | D11: Design Wallet data model in a new Financial Domain (Document 04 §6, Document 08) | E11: 🟨 Medium | F11: Phase 1 completion | H11: ⬜ Not Started
A12: FUT-011 | B12: Phase 2 — Payments, Wallet, Insights | C12: Wallet | D12: Implement wallet_transactions ledger (Document 04 §6) | E12: 🟨 Medium | F12: Phase 1 completion | H12: ⬜ Not Started
A13: FUT-012 | B13: Phase 2 — Payments, Wallet, Insights | C13: Business Insights | D13: Build Business Insights analytics module on top of Digital Business Profile (Document 08) | E13: 🟨 Medium | F13: Phase 1 completion | H13: ⬜ Not Started
... A25: FUT-024 | B25: Phase 4 — Partner APIs & Open Platform | C25: Open Platform Expansion | D25: Evaluate adjacent ecosystem services (logistics, insurance) on shared trust infrastructure (Document 08) | E25: 🟩 Low | F25: Phase 1 completion | H25: ⬜ Not Started

Sheet Notes & Assumptions
A1: TRU CONNECT: ENGINEERING ROADMAP: NOTES & ASSUMPTIONS
A3: SOURCE OF TRUTH
A4: Every task in this workbook is derived directly from Documents 00–09 (Project Vision, Product Specification, System UI/UX Specification, Frontend Component Specification, Database Design, Backend API Specification, Business Rules & Workflows, Data and Trust Engine, Product Roadmap, Ecosystem Strategy).
A6: DELIBERATE SCOPE EXCLUSIONS
A7: The roadmap-generator prompt template requested sheets/tasks for OCR, Receipt Upload, Invoice Parsing, a Credit Scoring/ML Engine, Fraud Detection, and a general-purpose Analytics Engine. None of these appear anywhere in Documents 00–09: Document 07 (Data and Trust Engine) explicitly states Phase 1 uses transparent, rule-based calculations, not ML models (§9), and Document 08 (Product Roadmap) does not mention receipts, OCR, or invoice parsing at any phase. Per the explicit instruction "Never invent features," this workbook does not include tasks for functionality that has no basis in the documentation. If TRU Connect intends to build these, they need their own source-of-truth documentation first — at that point this workbook can be extended with matching sheets.
A9: GROUNDED PROGRESS
A10: A handful of tasks are pre-marked "In Progress" or "Complete" rather than "Not Started", based on the current repository tree (structure.txt) supplied in this conversation: the Authentication Domain already has scaffolded backend files (user.py, user_repository.py, auth_service.py, auth_routes.py, auth_schemas.py, test_auth.py), backend core infrastructure files exist (config.py, extensions.py, base_model.py, decorators.py, exceptions.py, responses.py, logger.py, security.py), and the Supplier Product Catalogue frontend feature (screens, components, hooks, services, api) has been fully generated. Everything else defaults to Not Started — recalibrate freely as work actually progresses.
A12: ID SCHEME
A13: DB-xxx Database · BE-xxx Backend · API-xxx API · FE-xxx Frontend · TE-xxx Trust Engine · QA-xxx Testing · OPS-xxx DevOps · FUT-xxx Future Phases (2–4).
A15: DEPENDENCIES COLUMN
A16: Dependencies point to the most relevant upstream task or artifact (e.g. a Database migration ID a Backend model depends on). They are indicative of build order, not an exhaustive dependency graph — recalibrate during sprint planning.
A18: HOW TO USE THIS WORKBOOK
... A22: 4. Filter any sheet by Module, Priority, or Status using Excel's AutoFilter (enable via Data > Filter) to scope a sprint.
